{"accuracy": 57.29768172554348, "timestamp": 1755093828, "checkpoint_dir_name": null, "done": false, "training_iteration": 1, "trial_id": "8388b_00027", "date": "2025-08-13_10-03-48", "time_this_iter_s": 1.4742345809936523, "time_total_s": 1.4742345809936523, "pid": 22616, "hostname": "Maderfoker", "node_ip": "127.0.0.1", "config": {"base_lr": 0.017042054460252108, "batch_size": 1024, "l1_size": 311, "l1_drop": 0.28602644812467504, "l2_size": 545, "l2_drop": 0.050839328746976976, "l3_size": 574, "l3_drop": 0.27034336821003296, "l2_rate": 0.0010498877116058537, "t_max": 13, "max_epochs": 80}, "time_since_restore": 1.4742345809936523, "iterations_since_restore": 1}
{"accuracy": 81.12474524456522, "timestamp": 1755093829, "checkpoint_dir_name": null, "done": false, "training_iteration": 2, "trial_id": "8388b_00027", "date": "2025-08-13_10-03-49", "time_this_iter_s": 0.3852238655090332, "time_total_s": 1.8594584465026855, "pid": 22616, "hostname": "Maderfoker", "node_ip": "127.0.0.1", "config": {"base_lr": 0.017042054460252108, "batch_size": 1024, "l1_size": 311, "l1_drop": 0.28602644812467504, "l2_size": 545, "l2_drop": 0.050839328746976976, "l3_size": 574, "l3_drop": 0.27034336821003296, "l2_rate": 0.0010498877116058537, "t_max": 13, "max_epochs": 80}, "time_since_restore": 1.8594584465026855, "iterations_since_restore": 2}
{"accuracy": 80.62337239583333, "timestamp": 1755093829, "checkpoint_dir_name": null, "done": false, "training_iteration": 3, "trial_id": "8388b_00027", "date": "2025-08-13_10-03-49", "time_this_iter_s": 0.37395668029785156, "time_total_s": 2.233415126800537, "pid": 22616, "hostname": "Maderfoker", "node_ip": "127.0.0.1", "config": {"base_lr": 0.017042054460252108, "batch_size": 1024, "l1_size": 311, "l1_drop": 0.28602644812467504, "l2_size": 545, "l2_drop": 0.050839328746976976, "l3_size": 574, "l3_drop": 0.27034336821003296, "l2_rate": 0.0010498877116058537, "t_max": 13, "max_epochs": 80}, "time_since_restore": 2.233415126800537, "iterations_since_restore": 3}
{"accuracy": 84.03178781702898, "timestamp": 1755093830, "checkpoint_dir_name": null, "done": false, "training_iteration": 4, "trial_id": "8388b_00027", "date": "2025-08-13_10-03-50", "time_this_iter_s": 0.4111318588256836, "time_total_s": 2.6445469856262207, "pid": 22616, "hostname": "Maderfoker", "node_ip": "127.0.0.1", "config": {"base_lr": 0.017042054460252108, "batch_size": 1024, "l1_size": 311, "l1_drop": 0.28602644812467504, "l2_size": 545, "l2_drop": 0.050839328746976976, "l3_size": 574, "l3_drop": 0.27034336821003296, "l2_rate": 0.0010498877116058537, "t_max": 13, "max_epochs": 80}, "time_since_restore": 2.6445469856262207, "iterations_since_restore": 4}
{"accuracy": 81.57835144927536, "timestamp": 1755093830, "checkpoint_dir_name": null, "done": false, "training_iteration": 5, "trial_id": "8388b_00027", "date": "2025-08-13_10-03-50", "time_this_iter_s": 0.3601865768432617, "time_total_s": 3.0047335624694824, "pid": 22616, "hostname": "Maderfoker", "node_ip": "127.0.0.1", "config": {"base_lr": 0.017042054460252108, "batch_size": 1024, "l1_size": 311, "l1_drop": 0.28602644812467504, "l2_size": 545, "l2_drop": 0.050839328746976976, "l3_size": 574, "l3_drop": 0.27034336821003296, "l2_rate": 0.0010498877116058537, "t_max": 13, "max_epochs": 80}, "time_since_restore": 3.0047335624694824, "iterations_since_restore": 5}
{"accuracy": 84.18924082880434, "timestamp": 1755093830, "checkpoint_dir_name": null, "done": false, "training_iteration": 6, "trial_id": "8388b_00027", "date": "2025-08-13_10-03-50", "time_this_iter_s": 0.2999694347381592, "time_total_s": 3.3047029972076416, "pid": 22616, "hostname": "Maderfoker", "node_ip": "127.0.0.1", "config": {"base_lr": 0.017042054460252108, "batch_size": 1024, "l1_size": 311, "l1_drop": 0.28602644812467504, "l2_size": 545, "l2_drop": 0.050839328746976976, "l3_size": 574, "l3_drop": 0.27034336821003296, "l2_rate": 0.0010498877116058537, "t_max": 13, "max_epochs": 80}, "time_since_restore": 3.3047029972076416, "iterations_since_restore": 6}
{"accuracy": 84.12767493206522, "timestamp": 1755093831, "checkpoint_dir_name": null, "done": false, "training_iteration": 7, "trial_id": "8388b_00027", "date": "2025-08-13_10-03-51", "time_this_iter_s": 0.33664608001708984, "time_total_s": 3.6413490772247314, "pid": 22616, "hostname": "Maderfoker", "node_ip": "127.0.0.1", "config": {"base_lr": 0.017042054460252108, "batch_size": 1024, "l1_size": 311, "l1_drop": 0.28602644812467504, "l2_size": 545, "l2_drop": 0.050839328746976976, "l3_size": 574, "l3_drop": 0.27034336821003296, "l2_rate": 0.0010498877116058537, "t_max": 13, "max_epochs": 80}, "time_since_restore": 3.6413490772247314, "iterations_since_restore": 7}
{"accuracy": 83.85381283967392, "timestamp": 1755093831, "checkpoint_dir_name": null, "done": false, "training_iteration": 8, "trial_id": "8388b_00027", "date": "2025-08-13_10-03-51", "time_this_iter_s": 0.32983922958374023, "time_total_s": 3.9711883068084717, "pid": 22616, "hostname": "Maderfoker", "node_ip": "127.0.0.1", "config": {"base_lr": 0.017042054460252108, "batch_size": 1024, "l1_size": 311, "l1_drop": 0.28602644812467504, "l2_size": 545, "l2_drop": 0.050839328746976976, "l3_size": 574, "l3_drop": 0.27034336821003296, "l2_rate": 0.0010498877116058537, "t_max": 13, "max_epochs": 80}, "time_since_restore": 3.9711883068084717, "iterations_since_restore": 8}
{"accuracy": 85.97783627717392, "timestamp": 1755093831, "checkpoint_dir_name": null, "done": false, "training_iteration": 9, "trial_id": "8388b_00027", "date": "2025-08-13_10-03-51", "time_this_iter_s": 0.3874940872192383, "time_total_s": 4.35868239402771, "pid": 22616, "hostname": "Maderfoker", "node_ip": "127.0.0.1", "config": {"base_lr": 0.017042054460252108, "batch_size": 1024, "l1_size": 311, "l1_drop": 0.28602644812467504, "l2_size": 545, "l2_drop": 0.050839328746976976, "l3_size": 574, "l3_drop": 0.27034336821003296, "l2_rate": 0.0010498877116058537, "t_max": 13, "max_epochs": 80}, "time_since_restore": 4.35868239402771, "iterations_since_restore": 9}
{"accuracy": 87.3291015625, "timestamp": 1755093832, "checkpoint_dir_name": null, "done": true, "training_iteration": 10, "trial_id": "8388b_00027", "date": "2025-08-13_10-03-52", "time_this_iter_s": 0.3162105083465576, "time_total_s": 4.674892902374268, "pid": 22616, "hostname": "Maderfoker", "node_ip": "127.0.0.1", "config": {"base_lr": 0.017042054460252108, "batch_size": 1024, "l1_size": 311, "l1_drop": 0.28602644812467504, "l2_size": 545, "l2_drop": 0.050839328746976976, "l3_size": 574, "l3_drop": 0.27034336821003296, "l2_rate": 0.0010498877116058537, "t_max": 13, "max_epochs": 80}, "time_since_restore": 4.674892902374268, "iterations_since_restore": 10}
