{"accuracy": 84.41250566123189, "timestamp": 1755093525, "checkpoint_dir_name": null, "done": false, "training_iteration": 1, "trial_id": "8388b_00002", "date": "2025-08-13_09-58-45", "time_this_iter_s": 1.310142993927002, "time_total_s": 1.310142993927002, "pid": 34572, "hostname": "Maderfoker", "node_ip": "127.0.0.1", "config": {"base_lr": 0.0005039142631963092, "batch_size": 1024, "l1_size": 347, "l1_drop": 0.26081490149461595, "l2_size": 486, "l2_drop": 0.14705334228509317, "l3_size": 586, "l3_drop": 0.28084375363310715, "l2_rate": 0.001981137438410577, "t_max": 10, "max_epochs": 80}, "time_since_restore": 1.310142993927002, "iterations_since_restore": 1}
{"accuracy": 86.51989923007245, "timestamp": 1755093525, "checkpoint_dir_name": null, "done": false, "training_iteration": 2, "trial_id": "8388b_00002", "date": "2025-08-13_09-58-45", "time_this_iter_s": 0.3664848804473877, "time_total_s": 1.6766278743743896, "pid": 34572, "hostname": "Maderfoker", "node_ip": "127.0.0.1", "config": {"base_lr": 0.0005039142631963092, "batch_size": 1024, "l1_size": 347, "l1_drop": 0.26081490149461595, "l2_size": 486, "l2_drop": 0.14705334228509317, "l3_size": 586, "l3_drop": 0.28084375363310715, "l2_rate": 0.001981137438410577, "t_max": 10, "max_epochs": 80}, "time_since_restore": 1.6766278743743896, "iterations_since_restore": 2}
{"accuracy": 87.26152060688406, "timestamp": 1755093526, "checkpoint_dir_name": null, "done": false, "training_iteration": 3, "trial_id": "8388b_00002", "date": "2025-08-13_09-58-46", "time_this_iter_s": 0.3233470916748047, "time_total_s": 1.9999749660491943, "pid": 34572, "hostname": "Maderfoker", "node_ip": "127.0.0.1", "config": {"base_lr": 0.0005039142631963092, "batch_size": 1024, "l1_size": 347, "l1_drop": 0.26081490149461595, "l2_size": 486, "l2_drop": 0.14705334228509317, "l3_size": 586, "l3_drop": 0.28084375363310715, "l2_rate": 0.001981137438410577, "t_max": 10, "max_epochs": 80}, "time_since_restore": 1.9999749660491943, "iterations_since_restore": 3}
{"accuracy": 88.24303668478261, "timestamp": 1755093526, "checkpoint_dir_name": null, "done": false, "training_iteration": 4, "trial_id": "8388b_00002", "date": "2025-08-13_09-58-46", "time_this_iter_s": 0.3901698589324951, "time_total_s": 2.3901448249816895, "pid": 34572, "hostname": "Maderfoker", "node_ip": "127.0.0.1", "config": {"base_lr": 0.0005039142631963092, "batch_size": 1024, "l1_size": 347, "l1_drop": 0.26081490149461595, "l2_size": 486, "l2_drop": 0.14705334228509317, "l3_size": 586, "l3_drop": 0.28084375363310715, "l2_rate": 0.001981137438410577, "t_max": 10, "max_epochs": 80}, "time_since_restore": 2.3901448249816895, "iterations_since_restore": 4}
{"accuracy": 88.11176687047102, "timestamp": 1755093527, "checkpoint_dir_name": null, "done": false, "training_iteration": 5, "trial_id": "8388b_00002", "date": "2025-08-13_09-58-47", "time_this_iter_s": 0.3888986110687256, "time_total_s": 2.779043436050415, "pid": 34572, "hostname": "Maderfoker", "node_ip": "127.0.0.1", "config": {"base_lr": 0.0005039142631963092, "batch_size": 1024, "l1_size": 347, "l1_drop": 0.26081490149461595, "l2_size": 486, "l2_drop": 0.14705334228509317, "l3_size": 586, "l3_drop": 0.28084375363310715, "l2_rate": 0.001981137438410577, "t_max": 10, "max_epochs": 80}, "time_since_restore": 2.779043436050415, "iterations_since_restore": 5}
{"accuracy": 88.48753113677536, "timestamp": 1755093527, "checkpoint_dir_name": null, "done": false, "training_iteration": 6, "trial_id": "8388b_00002", "date": "2025-08-13_09-58-47", "time_this_iter_s": 0.3446369171142578, "time_total_s": 3.123680353164673, "pid": 34572, "hostname": "Maderfoker", "node_ip": "127.0.0.1", "config": {"base_lr": 0.0005039142631963092, "batch_size": 1024, "l1_size": 347, "l1_drop": 0.26081490149461595, "l2_size": 486, "l2_drop": 0.14705334228509317, "l3_size": 586, "l3_drop": 0.28084375363310715, "l2_rate": 0.001981137438410577, "t_max": 10, "max_epochs": 80}, "time_since_restore": 3.123680353164673, "iterations_since_restore": 6}
{"accuracy": 89.02959408967392, "timestamp": 1755093527, "checkpoint_dir_name": null, "done": false, "training_iteration": 7, "trial_id": "8388b_00002", "date": "2025-08-13_09-58-47", "time_this_iter_s": 0.37801289558410645, "time_total_s": 3.5016932487487793, "pid": 34572, "hostname": "Maderfoker", "node_ip": "127.0.0.1", "config": {"base_lr": 0.0005039142631963092, "batch_size": 1024, "l1_size": 347, "l1_drop": 0.26081490149461595, "l2_size": 486, "l2_drop": 0.14705334228509317, "l3_size": 586, "l3_drop": 0.28084375363310715, "l2_rate": 0.001981137438410577, "t_max": 10, "max_epochs": 80}, "time_since_restore": 3.5016932487487793, "iterations_since_restore": 7}
{"accuracy": 88.9931499094203, "timestamp": 1755093528, "checkpoint_dir_name": null, "done": false, "training_iteration": 8, "trial_id": "8388b_00002", "date": "2025-08-13_09-58-48", "time_this_iter_s": 0.31525182723999023, "time_total_s": 3.8169450759887695, "pid": 34572, "hostname": "Maderfoker", "node_ip": "127.0.0.1", "config": {"base_lr": 0.0005039142631963092, "batch_size": 1024, "l1_size": 347, "l1_drop": 0.26081490149461595, "l2_size": 486, "l2_drop": 0.14705334228509317, "l3_size": 586, "l3_drop": 0.28084375363310715, "l2_rate": 0.001981137438410577, "t_max": 10, "max_epochs": 80}, "time_since_restore": 3.8169450759887695, "iterations_since_restore": 8}
{"accuracy": 89.21004585597827, "timestamp": 1755093528, "checkpoint_dir_name": null, "done": false, "training_iteration": 9, "trial_id": "8388b_00002", "date": "2025-08-13_09-58-48", "time_this_iter_s": 0.36275768280029297, "time_total_s": 4.1797027587890625, "pid": 34572, "hostname": "Maderfoker", "node_ip": "127.0.0.1", "config": {"base_lr": 0.0005039142631963092, "batch_size": 1024, "l1_size": 347, "l1_drop": 0.26081490149461595, "l2_size": 486, "l2_drop": 0.14705334228509317, "l3_size": 586, "l3_drop": 0.28084375363310715, "l2_rate": 0.001981137438410577, "t_max": 10, "max_epochs": 80}, "time_since_restore": 4.1797027587890625, "iterations_since_restore": 9}
{"accuracy": 89.31159420289855, "timestamp": 1755093528, "checkpoint_dir_name": null, "done": false, "training_iteration": 10, "trial_id": "8388b_00002", "date": "2025-08-13_09-58-48", "time_this_iter_s": 0.3119018077850342, "time_total_s": 4.491604566574097, "pid": 34572, "hostname": "Maderfoker", "node_ip": "127.0.0.1", "config": {"base_lr": 0.0005039142631963092, "batch_size": 1024, "l1_size": 347, "l1_drop": 0.26081490149461595, "l2_size": 486, "l2_drop": 0.14705334228509317, "l3_size": 586, "l3_drop": 0.28084375363310715, "l2_rate": 0.001981137438410577, "t_max": 10, "max_epochs": 80}, "time_since_restore": 4.491604566574097, "iterations_since_restore": 10}
{"accuracy": 89.21429177989131, "timestamp": 1755093529, "checkpoint_dir_name": null, "done": false, "training_iteration": 11, "trial_id": "8388b_00002", "date": "2025-08-13_09-58-49", "time_this_iter_s": 0.35794711112976074, "time_total_s": 4.849551677703857, "pid": 34572, "hostname": "Maderfoker", "node_ip": "127.0.0.1", "config": {"base_lr": 0.0005039142631963092, "batch_size": 1024, "l1_size": 347, "l1_drop": 0.26081490149461595, "l2_size": 486, "l2_drop": 0.14705334228509317, "l3_size": 586, "l3_drop": 0.28084375363310715, "l2_rate": 0.001981137438410577, "t_max": 10, "max_epochs": 80}, "time_since_restore": 4.849551677703857, "iterations_since_restore": 11}
{"accuracy": 89.24082880434783, "timestamp": 1755093529, "checkpoint_dir_name": null, "done": false, "training_iteration": 12, "trial_id": "8388b_00002", "date": "2025-08-13_09-58-49", "time_this_iter_s": 0.36745357513427734, "time_total_s": 5.217005252838135, "pid": 34572, "hostname": "Maderfoker", "node_ip": "127.0.0.1", "config": {"base_lr": 0.0005039142631963092, "batch_size": 1024, "l1_size": 347, "l1_drop": 0.26081490149461595, "l2_size": 486, "l2_drop": 0.14705334228509317, "l3_size": 586, "l3_drop": 0.28084375363310715, "l2_rate": 0.001981137438410577, "t_max": 10, "max_epochs": 80}, "time_since_restore": 5.217005252838135, "iterations_since_restore": 12}
{"accuracy": 89.3310546875, "timestamp": 1755093529, "checkpoint_dir_name": null, "done": false, "training_iteration": 13, "trial_id": "8388b_00002", "date": "2025-08-13_09-58-49", "time_this_iter_s": 0.30977296829223633, "time_total_s": 5.526778221130371, "pid": 34572, "hostname": "Maderfoker", "node_ip": "127.0.0.1", "config": {"base_lr": 0.0005039142631963092, "batch_size": 1024, "l1_size": 347, "l1_drop": 0.26081490149461595, "l2_size": 486, "l2_drop": 0.14705334228509317, "l3_size": 586, "l3_drop": 0.28084375363310715, "l2_rate": 0.001981137438410577, "t_max": 10, "max_epochs": 80}, "time_since_restore": 5.526778221130371, "iterations_since_restore": 13}
{"accuracy": 89.45807857789855, "timestamp": 1755093530, "checkpoint_dir_name": null, "done": false, "training_iteration": 14, "trial_id": "8388b_00002", "date": "2025-08-13_09-58-50", "time_this_iter_s": 0.3596198558807373, "time_total_s": 5.886398077011108, "pid": 34572, "hostname": "Maderfoker", "node_ip": "127.0.0.1", "config": {"base_lr": 0.0005039142631963092, "batch_size": 1024, "l1_size": 347, "l1_drop": 0.26081490149461595, "l2_size": 486, "l2_drop": 0.14705334228509317, "l3_size": 586, "l3_drop": 0.28084375363310715, "l2_rate": 0.001981137438410577, "t_max": 10, "max_epochs": 80}, "time_since_restore": 5.886398077011108, "iterations_since_restore": 14}
{"accuracy": 89.03843976449275, "timestamp": 1755093530, "checkpoint_dir_name": null, "done": false, "training_iteration": 15, "trial_id": "8388b_00002", "date": "2025-08-13_09-58-50", "time_this_iter_s": 0.3715860843658447, "time_total_s": 6.257984161376953, "pid": 34572, "hostname": "Maderfoker", "node_ip": "127.0.0.1", "config": {"base_lr": 0.0005039142631963092, "batch_size": 1024, "l1_size": 347, "l1_drop": 0.26081490149461595, "l2_size": 486, "l2_drop": 0.14705334228509317, "l3_size": 586, "l3_drop": 0.28084375363310715, "l2_rate": 0.001981137438410577, "t_max": 10, "max_epochs": 80}, "time_since_restore": 6.257984161376953, "iterations_since_restore": 15}
{"accuracy": 89.3098250679348, "timestamp": 1755093530, "checkpoint_dir_name": null, "done": false, "training_iteration": 16, "trial_id": "8388b_00002", "date": "2025-08-13_09-58-50", "time_this_iter_s": 0.30832719802856445, "time_total_s": 6.566311359405518, "pid": 34572, "hostname": "Maderfoker", "node_ip": "127.0.0.1", "config": {"base_lr": 0.0005039142631963092, "batch_size": 1024, "l1_size": 347, "l1_drop": 0.26081490149461595, "l2_size": 486, "l2_drop": 0.14705334228509317, "l3_size": 586, "l3_drop": 0.28084375363310715, "l2_rate": 0.001981137438410577, "t_max": 10, "max_epochs": 80}, "time_since_restore": 6.566311359405518, "iterations_since_restore": 16}
{"accuracy": 89.2372905344203, "timestamp": 1755093531, "checkpoint_dir_name": null, "done": false, "training_iteration": 17, "trial_id": "8388b_00002", "date": "2025-08-13_09-58-51", "time_this_iter_s": 0.37625837326049805, "time_total_s": 6.942569732666016, "pid": 34572, "hostname": "Maderfoker", "node_ip": "127.0.0.1", "config": {"base_lr": 0.0005039142631963092, "batch_size": 1024, "l1_size": 347, "l1_drop": 0.26081490149461595, "l2_size": 486, "l2_drop": 0.14705334228509317, "l3_size": 586, "l3_drop": 0.28084375363310715, "l2_rate": 0.001981137438410577, "t_max": 10, "max_epochs": 80}, "time_since_restore": 6.942569732666016, "iterations_since_restore": 17}
{"accuracy": 89.46763190670289, "timestamp": 1755093531, "checkpoint_dir_name": null, "done": false, "training_iteration": 18, "trial_id": "8388b_00002", "date": "2025-08-13_09-58-51", "time_this_iter_s": 0.3137946128845215, "time_total_s": 7.256364345550537, "pid": 34572, "hostname": "Maderfoker", "node_ip": "127.0.0.1", "config": {"base_lr": 0.0005039142631963092, "batch_size": 1024, "l1_size": 347, "l1_drop": 0.26081490149461595, "l2_size": 486, "l2_drop": 0.14705334228509317, "l3_size": 586, "l3_drop": 0.28084375363310715, "l2_rate": 0.001981137438410577, "t_max": 10, "max_epochs": 80}, "time_since_restore": 7.256364345550537, "iterations_since_restore": 18}
{"accuracy": 89.16758661684783, "timestamp": 1755093531, "checkpoint_dir_name": null, "done": false, "training_iteration": 19, "trial_id": "8388b_00002", "date": "2025-08-13_09-58-51", "time_this_iter_s": 0.38021254539489746, "time_total_s": 7.636576890945435, "pid": 34572, "hostname": "Maderfoker", "node_ip": "127.0.0.1", "config": {"base_lr": 0.0005039142631963092, "batch_size": 1024, "l1_size": 347, "l1_drop": 0.26081490149461595, "l2_size": 486, "l2_drop": 0.14705334228509317, "l3_size": 586, "l3_drop": 0.28084375363310715, "l2_rate": 0.001981137438410577, "t_max": 10, "max_epochs": 80}, "time_since_restore": 7.636576890945435, "iterations_since_restore": 19}
{"accuracy": 88.82932801177536, "timestamp": 1755093532, "checkpoint_dir_name": null, "done": false, "training_iteration": 20, "trial_id": "8388b_00002", "date": "2025-08-13_09-58-52", "time_this_iter_s": 0.36992740631103516, "time_total_s": 8.00650429725647, "pid": 34572, "hostname": "Maderfoker", "node_ip": "127.0.0.1", "config": {"base_lr": 0.0005039142631963092, "batch_size": 1024, "l1_size": 347, "l1_drop": 0.26081490149461595, "l2_size": 486, "l2_drop": 0.14705334228509317, "l3_size": 586, "l3_drop": 0.28084375363310715, "l2_rate": 0.001981137438410577, "t_max": 10, "max_epochs": 80}, "time_since_restore": 8.00650429725647, "iterations_since_restore": 20}
{"accuracy": 89.00376471920289, "timestamp": 1755093532, "checkpoint_dir_name": null, "done": false, "training_iteration": 21, "trial_id": "8388b_00002", "date": "2025-08-13_09-58-52", "time_this_iter_s": 0.3114190101623535, "time_total_s": 8.317923307418823, "pid": 34572, "hostname": "Maderfoker", "node_ip": "127.0.0.1", "config": {"base_lr": 0.0005039142631963092, "batch_size": 1024, "l1_size": 347, "l1_drop": 0.26081490149461595, "l2_size": 486, "l2_drop": 0.14705334228509317, "l3_size": 586, "l3_drop": 0.28084375363310715, "l2_rate": 0.001981137438410577, "t_max": 10, "max_epochs": 80}, "time_since_restore": 8.317923307418823, "iterations_since_restore": 21}
{"accuracy": 88.71185745018117, "timestamp": 1755093532, "checkpoint_dir_name": null, "done": false, "training_iteration": 22, "trial_id": "8388b_00002", "date": "2025-08-13_09-58-52", "time_this_iter_s": 0.3628201484680176, "time_total_s": 8.68074345588684, "pid": 34572, "hostname": "Maderfoker", "node_ip": "127.0.0.1", "config": {"base_lr": 0.0005039142631963092, "batch_size": 1024, "l1_size": 347, "l1_drop": 0.26081490149461595, "l2_size": 486, "l2_drop": 0.14705334228509317, "l3_size": 586, "l3_drop": 0.28084375363310715, "l2_rate": 0.001981137438410577, "t_max": 10, "max_epochs": 80}, "time_since_restore": 8.68074345588684, "iterations_since_restore": 22}
{"accuracy": 89.29921025815217, "timestamp": 1755093533, "checkpoint_dir_name": null, "done": false, "training_iteration": 23, "trial_id": "8388b_00002", "date": "2025-08-13_09-58-53", "time_this_iter_s": 0.31281018257141113, "time_total_s": 8.993553638458252, "pid": 34572, "hostname": "Maderfoker", "node_ip": "127.0.0.1", "config": {"base_lr": 0.0005039142631963092, "batch_size": 1024, "l1_size": 347, "l1_drop": 0.26081490149461595, "l2_size": 486, "l2_drop": 0.14705334228509317, "l3_size": 586, "l3_drop": 0.28084375363310715, "l2_rate": 0.001981137438410577, "t_max": 10, "max_epochs": 80}, "time_since_restore": 8.993553638458252, "iterations_since_restore": 23}
{"accuracy": 89.14989526721014, "timestamp": 1755093533, "checkpoint_dir_name": null, "done": false, "training_iteration": 24, "trial_id": "8388b_00002", "date": "2025-08-13_09-58-53", "time_this_iter_s": 0.37003159523010254, "time_total_s": 9.363585233688354, "pid": 34572, "hostname": "Maderfoker", "node_ip": "127.0.0.1", "config": {"base_lr": 0.0005039142631963092, "batch_size": 1024, "l1_size": 347, "l1_drop": 0.26081490149461595, "l2_size": 486, "l2_drop": 0.14705334228509317, "l3_size": 586, "l3_drop": 0.28084375363310715, "l2_rate": 0.001981137438410577, "t_max": 10, "max_epochs": 80}, "time_since_restore": 9.363585233688354, "iterations_since_restore": 24}
{"accuracy": 89.71212635869564, "timestamp": 1755093534, "checkpoint_dir_name": null, "done": false, "training_iteration": 25, "trial_id": "8388b_00002", "date": "2025-08-13_09-58-54", "time_this_iter_s": 0.3681454658508301, "time_total_s": 9.731730699539185, "pid": 34572, "hostname": "Maderfoker", "node_ip": "127.0.0.1", "config": {"base_lr": 0.0005039142631963092, "batch_size": 1024, "l1_size": 347, "l1_drop": 0.26081490149461595, "l2_size": 486, "l2_drop": 0.14705334228509317, "l3_size": 586, "l3_drop": 0.28084375363310715, "l2_rate": 0.001981137438410577, "t_max": 10, "max_epochs": 80}, "time_since_restore": 9.731730699539185, "iterations_since_restore": 25}
{"accuracy": 89.53556668931161, "timestamp": 1755093534, "checkpoint_dir_name": null, "done": false, "training_iteration": 26, "trial_id": "8388b_00002", "date": "2025-08-13_09-58-54", "time_this_iter_s": 0.3099792003631592, "time_total_s": 10.041709899902344, "pid": 34572, "hostname": "Maderfoker", "node_ip": "127.0.0.1", "config": {"base_lr": 0.0005039142631963092, "batch_size": 1024, "l1_size": 347, "l1_drop": 0.26081490149461595, "l2_size": 486, "l2_drop": 0.14705334228509317, "l3_size": 586, "l3_drop": 0.28084375363310715, "l2_rate": 0.001981137438410577, "t_max": 10, "max_epochs": 80}, "time_since_restore": 10.041709899902344, "iterations_since_restore": 26}
{"accuracy": 90.00367980072464, "timestamp": 1755093534, "checkpoint_dir_name": null, "done": false, "training_iteration": 27, "trial_id": "8388b_00002", "date": "2025-08-13_09-58-54", "time_this_iter_s": 0.34996509552001953, "time_total_s": 10.391674995422363, "pid": 34572, "hostname": "Maderfoker", "node_ip": "127.0.0.1", "config": {"base_lr": 0.0005039142631963092, "batch_size": 1024, "l1_size": 347, "l1_drop": 0.26081490149461595, "l2_size": 486, "l2_drop": 0.14705334228509317, "l3_size": 586, "l3_drop": 0.28084375363310715, "l2_rate": 0.001981137438410577, "t_max": 10, "max_epochs": 80}, "time_since_restore": 10.391674995422363, "iterations_since_restore": 27}
{"accuracy": 90.50965240036231, "timestamp": 1755093534, "checkpoint_dir_name": null, "done": false, "training_iteration": 28, "trial_id": "8388b_00002", "date": "2025-08-13_09-58-54", "time_this_iter_s": 0.29305386543273926, "time_total_s": 10.684728860855103, "pid": 34572, "hostname": "Maderfoker", "node_ip": "127.0.0.1", "config": {"base_lr": 0.0005039142631963092, "batch_size": 1024, "l1_size": 347, "l1_drop": 0.26081490149461595, "l2_size": 486, "l2_drop": 0.14705334228509317, "l3_size": 586, "l3_drop": 0.28084375363310715, "l2_rate": 0.001981137438410577, "t_max": 10, "max_epochs": 80}, "time_since_restore": 10.684728860855103, "iterations_since_restore": 28}
{"accuracy": 90.46577785326087, "timestamp": 1755093535, "checkpoint_dir_name": null, "done": false, "training_iteration": 29, "trial_id": "8388b_00002", "date": "2025-08-13_09-58-55", "time_this_iter_s": 0.3535270690917969, "time_total_s": 11.0382559299469, "pid": 34572, "hostname": "Maderfoker", "node_ip": "127.0.0.1", "config": {"base_lr": 0.0005039142631963092, "batch_size": 1024, "l1_size": 347, "l1_drop": 0.26081490149461595, "l2_size": 486, "l2_drop": 0.14705334228509317, "l3_size": 586, "l3_drop": 0.28084375363310715, "l2_rate": 0.001981137438410577, "t_max": 10, "max_epochs": 80}, "time_since_restore": 11.0382559299469, "iterations_since_restore": 29}
{"accuracy": 90.55954200634058, "timestamp": 1755093535, "checkpoint_dir_name": null, "done": false, "training_iteration": 30, "trial_id": "8388b_00002", "date": "2025-08-13_09-58-55", "time_this_iter_s": 0.35149049758911133, "time_total_s": 11.38974642753601, "pid": 34572, "hostname": "Maderfoker", "node_ip": "127.0.0.1", "config": {"base_lr": 0.0005039142631963092, "batch_size": 1024, "l1_size": 347, "l1_drop": 0.26081490149461595, "l2_size": 486, "l2_drop": 0.14705334228509317, "l3_size": 586, "l3_drop": 0.28084375363310715, "l2_rate": 0.001981137438410577, "t_max": 10, "max_epochs": 80}, "time_since_restore": 11.38974642753601, "iterations_since_restore": 30}
{"accuracy": 90.5029296875, "timestamp": 1755093535, "checkpoint_dir_name": null, "done": false, "training_iteration": 31, "trial_id": "8388b_00002", "date": "2025-08-13_09-58-55", "time_this_iter_s": 0.3121793270111084, "time_total_s": 11.70192575454712, "pid": 34572, "hostname": "Maderfoker", "node_ip": "127.0.0.1", "config": {"base_lr": 0.0005039142631963092, "batch_size": 1024, "l1_size": 347, "l1_drop": 0.26081490149461595, "l2_size": 486, "l2_drop": 0.14705334228509317, "l3_size": 586, "l3_drop": 0.28084375363310715, "l2_rate": 0.001981137438410577, "t_max": 10, "max_epochs": 80}, "time_since_restore": 11.70192575454712, "iterations_since_restore": 31}
{"accuracy": 90.55883435235506, "timestamp": 1755093536, "checkpoint_dir_name": null, "done": false, "training_iteration": 32, "trial_id": "8388b_00002", "date": "2025-08-13_09-58-56", "time_this_iter_s": 0.3703172206878662, "time_total_s": 12.072242975234985, "pid": 34572, "hostname": "Maderfoker", "node_ip": "127.0.0.1", "config": {"base_lr": 0.0005039142631963092, "batch_size": 1024, "l1_size": 347, "l1_drop": 0.26081490149461595, "l2_size": 486, "l2_drop": 0.14705334228509317, "l3_size": 586, "l3_drop": 0.28084375363310715, "l2_rate": 0.001981137438410577, "t_max": 10, "max_epochs": 80}, "time_since_restore": 12.072242975234985, "iterations_since_restore": 32}
{"accuracy": 90.55211163949275, "timestamp": 1755093536, "checkpoint_dir_name": null, "done": false, "training_iteration": 33, "trial_id": "8388b_00002", "date": "2025-08-13_09-58-56", "time_this_iter_s": 0.3098948001861572, "time_total_s": 12.382137775421143, "pid": 34572, "hostname": "Maderfoker", "node_ip": "127.0.0.1", "config": {"base_lr": 0.0005039142631963092, "batch_size": 1024, "l1_size": 347, "l1_drop": 0.26081490149461595, "l2_size": 486, "l2_drop": 0.14705334228509317, "l3_size": 586, "l3_drop": 0.28084375363310715, "l2_rate": 0.001981137438410577, "t_max": 10, "max_epochs": 80}, "time_since_restore": 12.382137775421143, "iterations_since_restore": 33}
{"accuracy": 90.2839107789855, "timestamp": 1755093537, "checkpoint_dir_name": null, "done": false, "training_iteration": 34, "trial_id": "8388b_00002", "date": "2025-08-13_09-58-57", "time_this_iter_s": 0.3858928680419922, "time_total_s": 12.768030643463135, "pid": 34572, "hostname": "Maderfoker", "node_ip": "127.0.0.1", "config": {"base_lr": 0.0005039142631963092, "batch_size": 1024, "l1_size": 347, "l1_drop": 0.26081490149461595, "l2_size": 486, "l2_drop": 0.14705334228509317, "l3_size": 586, "l3_drop": 0.28084375363310715, "l2_rate": 0.001981137438410577, "t_max": 10, "max_epochs": 80}, "time_since_restore": 12.768030643463135, "iterations_since_restore": 34}
{"accuracy": 90.02066349637681, "timestamp": 1755093537, "checkpoint_dir_name": null, "done": false, "training_iteration": 35, "trial_id": "8388b_00002", "date": "2025-08-13_09-58-57", "time_this_iter_s": 0.40403246879577637, "time_total_s": 13.172063112258911, "pid": 34572, "hostname": "Maderfoker", "node_ip": "127.0.0.1", "config": {"base_lr": 0.0005039142631963092, "batch_size": 1024, "l1_size": 347, "l1_drop": 0.26081490149461595, "l2_size": 486, "l2_drop": 0.14705334228509317, "l3_size": 586, "l3_drop": 0.28084375363310715, "l2_rate": 0.001981137438410577, "t_max": 10, "max_epochs": 80}, "time_since_restore": 13.172063112258911, "iterations_since_restore": 35}
{"accuracy": 89.78713768115942, "timestamp": 1755093537, "checkpoint_dir_name": null, "done": false, "training_iteration": 36, "trial_id": "8388b_00002", "date": "2025-08-13_09-58-57", "time_this_iter_s": 0.3421146869659424, "time_total_s": 13.514177799224854, "pid": 34572, "hostname": "Maderfoker", "node_ip": "127.0.0.1", "config": {"base_lr": 0.0005039142631963092, "batch_size": 1024, "l1_size": 347, "l1_drop": 0.26081490149461595, "l2_size": 486, "l2_drop": 0.14705334228509317, "l3_size": 586, "l3_drop": 0.28084375363310715, "l2_rate": 0.001981137438410577, "t_max": 10, "max_epochs": 80}, "time_since_restore": 13.514177799224854, "iterations_since_restore": 36}
{"accuracy": 89.64489923007245, "timestamp": 1755093538, "checkpoint_dir_name": null, "done": false, "training_iteration": 37, "trial_id": "8388b_00002", "date": "2025-08-13_09-58-58", "time_this_iter_s": 0.3676879405975342, "time_total_s": 13.881865739822388, "pid": 34572, "hostname": "Maderfoker", "node_ip": "127.0.0.1", "config": {"base_lr": 0.0005039142631963092, "batch_size": 1024, "l1_size": 347, "l1_drop": 0.26081490149461595, "l2_size": 486, "l2_drop": 0.14705334228509317, "l3_size": 586, "l3_drop": 0.28084375363310715, "l2_rate": 0.001981137438410577, "t_max": 10, "max_epochs": 80}, "time_since_restore": 13.881865739822388, "iterations_since_restore": 37}
{"accuracy": 88.90115489130436, "timestamp": 1755093538, "checkpoint_dir_name": null, "done": false, "training_iteration": 38, "trial_id": "8388b_00002", "date": "2025-08-13_09-58-58", "time_this_iter_s": 0.3138742446899414, "time_total_s": 14.195739984512329, "pid": 34572, "hostname": "Maderfoker", "node_ip": "127.0.0.1", "config": {"base_lr": 0.0005039142631963092, "batch_size": 1024, "l1_size": 347, "l1_drop": 0.26081490149461595, "l2_size": 486, "l2_drop": 0.14705334228509317, "l3_size": 586, "l3_drop": 0.28084375363310715, "l2_rate": 0.001981137438410577, "t_max": 10, "max_epochs": 80}, "time_since_restore": 14.195739984512329, "iterations_since_restore": 38}
{"accuracy": 89.7011577219203, "timestamp": 1755093538, "checkpoint_dir_name": null, "done": false, "training_iteration": 39, "trial_id": "8388b_00002", "date": "2025-08-13_09-58-58", "time_this_iter_s": 0.36638545989990234, "time_total_s": 14.562125444412231, "pid": 34572, "hostname": "Maderfoker", "node_ip": "127.0.0.1", "config": {"base_lr": 0.0005039142631963092, "batch_size": 1024, "l1_size": 347, "l1_drop": 0.26081490149461595, "l2_size": 486, "l2_drop": 0.14705334228509317, "l3_size": 586, "l3_drop": 0.28084375363310715, "l2_rate": 0.001981137438410577, "t_max": 10, "max_epochs": 80}, "time_since_restore": 14.562125444412231, "iterations_since_restore": 39}
{"accuracy": 89.53308990036231, "timestamp": 1755093539, "checkpoint_dir_name": null, "done": false, "training_iteration": 40, "trial_id": "8388b_00002", "date": "2025-08-13_09-58-59", "time_this_iter_s": 0.36011481285095215, "time_total_s": 14.922240257263184, "pid": 34572, "hostname": "Maderfoker", "node_ip": "127.0.0.1", "config": {"base_lr": 0.0005039142631963092, "batch_size": 1024, "l1_size": 347, "l1_drop": 0.26081490149461595, "l2_size": 486, "l2_drop": 0.14705334228509317, "l3_size": 586, "l3_drop": 0.28084375363310715, "l2_rate": 0.001981137438410577, "t_max": 10, "max_epochs": 80}, "time_since_restore": 14.922240257263184, "iterations_since_restore": 40}
{"accuracy": 89.56422667572464, "timestamp": 1755093539, "checkpoint_dir_name": null, "done": false, "training_iteration": 41, "trial_id": "8388b_00002", "date": "2025-08-13_09-58-59", "time_this_iter_s": 0.3080604076385498, "time_total_s": 15.230300664901733, "pid": 34572, "hostname": "Maderfoker", "node_ip": "127.0.0.1", "config": {"base_lr": 0.0005039142631963092, "batch_size": 1024, "l1_size": 347, "l1_drop": 0.26081490149461595, "l2_size": 486, "l2_drop": 0.14705334228509317, "l3_size": 586, "l3_drop": 0.28084375363310715, "l2_rate": 0.001981137438410577, "t_max": 10, "max_epochs": 80}, "time_since_restore": 15.230300664901733, "iterations_since_restore": 41}
{"accuracy": 89.65374490489131, "timestamp": 1755093539, "checkpoint_dir_name": null, "done": false, "training_iteration": 42, "trial_id": "8388b_00002", "date": "2025-08-13_09-58-59", "time_this_iter_s": 0.3584861755371094, "time_total_s": 15.588786840438843, "pid": 34572, "hostname": "Maderfoker", "node_ip": "127.0.0.1", "config": {"base_lr": 0.0005039142631963092, "batch_size": 1024, "l1_size": 347, "l1_drop": 0.26081490149461595, "l2_size": 486, "l2_drop": 0.14705334228509317, "l3_size": 586, "l3_drop": 0.28084375363310715, "l2_rate": 0.001981137438410577, "t_max": 10, "max_epochs": 80}, "time_since_restore": 15.588786840438843, "iterations_since_restore": 42}
{"accuracy": 89.53273607336956, "timestamp": 1755093540, "checkpoint_dir_name": null, "done": false, "training_iteration": 43, "trial_id": "8388b_00002", "date": "2025-08-13_09-59-00", "time_this_iter_s": 0.32013678550720215, "time_total_s": 15.908923625946045, "pid": 34572, "hostname": "Maderfoker", "node_ip": "127.0.0.1", "config": {"base_lr": 0.0005039142631963092, "batch_size": 1024, "l1_size": 347, "l1_drop": 0.26081490149461595, "l2_size": 486, "l2_drop": 0.14705334228509317, "l3_size": 586, "l3_drop": 0.28084375363310715, "l2_rate": 0.001981137438410577, "t_max": 10, "max_epochs": 80}, "time_since_restore": 15.908923625946045, "iterations_since_restore": 43}
{"accuracy": 89.88620923913044, "timestamp": 1755093540, "checkpoint_dir_name": null, "done": false, "training_iteration": 44, "trial_id": "8388b_00002", "date": "2025-08-13_09-59-00", "time_this_iter_s": 0.35477232933044434, "time_total_s": 16.26369595527649, "pid": 34572, "hostname": "Maderfoker", "node_ip": "127.0.0.1", "config": {"base_lr": 0.0005039142631963092, "batch_size": 1024, "l1_size": 347, "l1_drop": 0.26081490149461595, "l2_size": 486, "l2_drop": 0.14705334228509317, "l3_size": 586, "l3_drop": 0.28084375363310715, "l2_rate": 0.001981137438410577, "t_max": 10, "max_epochs": 80}, "time_since_restore": 16.26369595527649, "iterations_since_restore": 44}
{"accuracy": 89.33848505434783, "timestamp": 1755093540, "checkpoint_dir_name": null, "done": false, "training_iteration": 45, "trial_id": "8388b_00002", "date": "2025-08-13_09-59-00", "time_this_iter_s": 0.3598616123199463, "time_total_s": 16.623557567596436, "pid": 34572, "hostname": "Maderfoker", "node_ip": "127.0.0.1", "config": {"base_lr": 0.0005039142631963092, "batch_size": 1024, "l1_size": 347, "l1_drop": 0.26081490149461595, "l2_size": 486, "l2_drop": 0.14705334228509317, "l3_size": 586, "l3_drop": 0.28084375363310715, "l2_rate": 0.001981137438410577, "t_max": 10, "max_epochs": 80}, "time_since_restore": 16.623557567596436, "iterations_since_restore": 45}
{"accuracy": 89.892578125, "timestamp": 1755093541, "checkpoint_dir_name": null, "done": false, "training_iteration": 46, "trial_id": "8388b_00002", "date": "2025-08-13_09-59-01", "time_this_iter_s": 0.3073453903198242, "time_total_s": 16.93090295791626, "pid": 34572, "hostname": "Maderfoker", "node_ip": "127.0.0.1", "config": {"base_lr": 0.0005039142631963092, "batch_size": 1024, "l1_size": 347, "l1_drop": 0.26081490149461595, "l2_size": 486, "l2_drop": 0.14705334228509317, "l3_size": 586, "l3_drop": 0.28084375363310715, "l2_rate": 0.001981137438410577, "t_max": 10, "max_epochs": 80}, "time_since_restore": 16.93090295791626, "iterations_since_restore": 46}
{"accuracy": 90.39005887681161, "timestamp": 1755093541, "checkpoint_dir_name": null, "done": false, "training_iteration": 47, "trial_id": "8388b_00002", "date": "2025-08-13_09-59-01", "time_this_iter_s": 0.37021422386169434, "time_total_s": 17.301117181777954, "pid": 34572, "hostname": "Maderfoker", "node_ip": "127.0.0.1", "config": {"base_lr": 0.0005039142631963092, "batch_size": 1024, "l1_size": 347, "l1_drop": 0.26081490149461595, "l2_size": 486, "l2_drop": 0.14705334228509317, "l3_size": 586, "l3_drop": 0.28084375363310715, "l2_rate": 0.001981137438410577, "t_max": 10, "max_epochs": 80}, "time_since_restore": 17.301117181777954, "iterations_since_restore": 47}
{"accuracy": 90.51212918931161, "timestamp": 1755093541, "checkpoint_dir_name": null, "done": false, "training_iteration": 48, "trial_id": "8388b_00002", "date": "2025-08-13_09-59-01", "time_this_iter_s": 0.30541300773620605, "time_total_s": 17.60653018951416, "pid": 34572, "hostname": "Maderfoker", "node_ip": "127.0.0.1", "config": {"base_lr": 0.0005039142631963092, "batch_size": 1024, "l1_size": 347, "l1_drop": 0.26081490149461595, "l2_size": 486, "l2_drop": 0.14705334228509317, "l3_size": 586, "l3_drop": 0.28084375363310715, "l2_rate": 0.001981137438410577, "t_max": 10, "max_epochs": 80}, "time_since_restore": 17.60653018951416, "iterations_since_restore": 48}
{"accuracy": 90.60943161231883, "timestamp": 1755093542, "checkpoint_dir_name": null, "done": false, "training_iteration": 49, "trial_id": "8388b_00002", "date": "2025-08-13_09-59-02", "time_this_iter_s": 0.3598215579986572, "time_total_s": 17.966351747512817, "pid": 34572, "hostname": "Maderfoker", "node_ip": "127.0.0.1", "config": {"base_lr": 0.0005039142631963092, "batch_size": 1024, "l1_size": 347, "l1_drop": 0.26081490149461595, "l2_size": 486, "l2_drop": 0.14705334228509317, "l3_size": 586, "l3_drop": 0.28084375363310715, "l2_rate": 0.001981137438410577, "t_max": 10, "max_epochs": 80}, "time_since_restore": 17.966351747512817, "iterations_since_restore": 49}
{"accuracy": 90.68161231884058, "timestamp": 1755093542, "checkpoint_dir_name": null, "done": true, "training_iteration": 50, "trial_id": "8388b_00002", "date": "2025-08-13_09-59-02", "time_this_iter_s": 0.36702775955200195, "time_total_s": 18.33337950706482, "pid": 34572, "hostname": "Maderfoker", "node_ip": "127.0.0.1", "config": {"base_lr": 0.0005039142631963092, "batch_size": 1024, "l1_size": 347, "l1_drop": 0.26081490149461595, "l2_size": 486, "l2_drop": 0.14705334228509317, "l3_size": 586, "l3_drop": 0.28084375363310715, "l2_rate": 0.001981137438410577, "t_max": 10, "max_epochs": 80}, "time_since_restore": 18.33337950706482, "iterations_since_restore": 50}
